[
    {
        "id": 1,
        "image": "/images/course-1.png",
        "title": "Personal traning",
        "description": "You’ll look at graphs and charts in Task One, how to approach the task and the language needed for a successful answer."
    },
    {
        "id": 2,
        "image": "/images/couse-2.png",
        "title": "Group traning",
        "description": "You’ll look at graphs and charts in Task One, how to approach the task and the language needed for a successful answer."
    }
]
